OcrReqPackage/__init__.py
OcrReqPackage/ocr_req_or_not.py
pdf_OCR_Req-0.2.dist-info/LICENSE.txt
pdf_OCR_Req-0.2.dist-info/METADATA
pdf_OCR_Req-0.2.dist-info/WHEEL
pdf_OCR_Req-0.2.dist-info/top_level.txt
pdf_OCR_Req-0.2.dist-info/RECORD
